rubier/__init__.py
rubier/colors.py
rubier/copyrights.py
rubier/encryptor.py
rubier/httpz.py
rubier/randomStream.py
rubier/rubier.py
rubier/servers.py
rubier/setup.py
rubier-3.9.5.dist-info/LICENSE.txt
rubier-3.9.5.dist-info/METADATA
rubier-3.9.5.dist-info/WHEEL
rubier-3.9.5.dist-info/top_level.txt
rubier-3.9.5.dist-info/RECORD
