Metadata-Version: 2.1
Name: rubier
Version: 3.9.5
Summary: Rubino Library
Home-page: https://github.com/HostBlack1Let/MyBale
Download-URL: https://github.com/user/reponame/archive/v_01.tar.gz
Author: Host1let
Author-email: sqlmapssh@gmail.com
License: MIT
Keywords: rubier
Classifier: Development Status :: 3 - Alpha
Classifier: Intended Audience :: Developers
Classifier: Topic :: Software Development :: Build Tools
Classifier: License :: OSI Approved :: MIT License
Classifier: Programming Language :: Python :: 3
Classifier: Programming Language :: Python :: 3.4
Classifier: Programming Language :: Python :: 3.5
Classifier: Programming Language :: Python :: 3.6
License-File: LICENSE.txt
Requires-Dist: requests
Requires-Dist: httpx
Requires-Dist: asyncio
Requires-Dist: aiohttp
